aia_read_svc/__init__.py
aia_read_svc/daemon.py
aia_read_svc/model/read_model.py
aia_read_svc/model/wh40k_enum.py
aia_read_svc/model/wh40k_model.py
aia_read_svc/numbers_to_letters.py
aia_read_svc/read_svc.py
aia_read_svc/repositories/__init__.py
aia_read_svc/repositories/aiaRepo.py
aia_read_svc/repositories/aiaWh40kRepo.py
aia_read_svc/wh40kSvc.py
aia_read_svc/whatsappSvc.py
aia_read_svc/yahooMailSvc.py
aia_read_svc-0.6.2.dist-info/METADATA
aia_read_svc-0.6.2.dist-info/WHEEL
aia_read_svc-0.6.2.dist-info/entry_points.txt
aia_read_svc-0.6.2.dist-info/RECORD
