Metadata-Version: 2.3
Name: aia-read-svc
Version: 0.6.2
Summary: 
Author: Edgar Rodrigo Sanchez De Gracia
Author-email: edgr.sanchez@mercadolibre.cl
Requires-Python: >=3.11.2,<3.14
Classifier: Programming Language :: Python :: 3
Classifier: Programming Language :: Python :: 3.12
Classifier: Programming Language :: Python :: 3.13
Requires-Dist: aia-utils (==0.4.5)
Requires-Dist: beautifulsoup4 (>=4.12.2,<5.0.0)
Requires-Dist: coverage (>=7.3.2,<8.0.0)
Requires-Dist: html-to-json (>=2.0.0,<3.0.0)
Requires-Dist: httpx (>=0.25.2,<0.26.0)
Requires-Dist: jmespath (>=1.0.1,<2.0.0)
Requires-Dist: numpy (>=1.24.0,<2.0.0)
Requires-Dist: openai (>=1.3.8,<2.0.0)
Requires-Dist: parsel (>=1.8.1,<2.0.0)
Requires-Dist: poetry (>=1.7.1,<2.0.0)
Requires-Dist: pyautogui (>=0.9.54,<0.10.0)
Requires-Dist: pywhatkit (==5.4)
Requires-Dist: rapidfuzz (>=3.0.0,<4.0.0)
Requires-Dist: requests (>=2.31.0,<3.0.0)
Requires-Dist: selenium (>=4.23.1,<5.0.0)
Requires-Dist: whatsapp-web (>=0.0.1,<0.0.2)
